{
  
    
        "post0": {
            "title": "Daily Git Commands",
            "content": "Introduction . git is a version control system that is widely used in software development. It is a distributed version control system that allows developers to work on the same project at the same time. It is also a powerful tool that can be used to track changes in files and revert to previous versions. . Git Workflow . . Git Stages . Staging area is a concept that is often used in git. It is a temporary area where files are stored before they are committed to the repository. . Usage . Create a new repository . # create a new directory $ mkdir myproject # change directory $ cd myproject # initialize the directory as a git repository $ git init . Clone an existing repository . # clone the repository $ git clone https://github.com/ian729/silver-umbrella.git . Add files to the staging area . # add all files in the current directory to the staging area $ git add -A # add a specific file to the staging area $ git add README.md . Commit changes . # commit all changes in the staging area $ git commit -m &quot;commit message&quot; . Push changes to remote repository . # push changes to remote repository $ git push . Mixed reset(default) . # reset all changes in the staging area $ git reset $ git reset --mixed # reset a specific file in the staging area $ git reset README.md . Hard reset . # hard reset all changes in the staging area $ git reset --hard # hard reset a specific file in the staging area $ git reset --hard README.md . Soft reset . # soft reset all changes in the staging area $ git reset --soft # soft reset a specific file in the staging area $ git reset --soft README.md . Difference between three reset types . | Type | Staging Area | Working Directory | | — | — | — | | Mixed | Reset | Not Reset | | Hard | Reset | Reset | | Soft | Not Reset | Not Reset | . . Revert changes . # revert all changes in the staging area $ git checkout -- . # revert a specific file in the staging area $ git checkout -- README.md . Squash commits . # squash the last 3 commits into one $ git rebase -i HEAD~3 . Pull changes from remote repository . # pull changes from remote repository $ git pull # pull changes while rebasing local commits $ git pull --rebase . . References . Git Documentation | Git Tutorial | Git Cheat Sheet | Git Cheat Sheet | Git Cheat Sheet |",
            "url": "https://ian729.github.io/silver-umbrella/markdown/tech/2022/10/05/GitIntroduction.html",
            "relUrl": "/markdown/tech/2022/10/05/GitIntroduction.html",
            "date": " • Oct 5, 2022"
        }
        
    
  
    
        ,"post1": {
            "title": "Shell Command xargs",
            "content": "Introduction . xargs is a command that reads data from the standard input and executes a command with the data as arguments. It is used to build and execute command lines from standard input. . Usage . Normally when we want to create a file with a specific name, we would do something like this: . touch NewFile.txt . With xargs, we can do the same thing: . echo &quot;NewFile.txt&quot; | xargs touch . Differences between xargs and pipe . In Linux, pipe is used to connect the output of one command to the input of another command. For example, we can use ls to list all files in the current directory, and then use grep to filter the files that contain a specific string. The following command will list all files that contain the string test: . ls | grep test . This works when the second command accepts standard input. However, if the second command does not accept standard input, e.g. touch we need to use xargs to parse the content into argument list. For example: . # if you echo new filename and pipe to touch # it will prompt error $ echo &quot;NewFile&quot; | touch usage: touch [-A [-][[hh]mm]SS] [-achm] [-r file] [-t [[CC]YY]MMDDhhmm[.SS]] [-d YYYY-MM-DDThh:mm:SS[.frac][tz]] file # This happens when the second command does not accept standard input # touch is a command that only accepts filename as argument # Correct Usage: $ touch &quot;NewFile.txt&quot; # Using xargs to transform the content into argument list $ echo &quot;NewFile.txt&quot; | xargs touch . Another Example is wc: . # if you echo a string and pipe to wc $ echo &quot;hello world&quot; | wc 1 2 12 # this is because wc only accepts standard input instead of argument list $ wc Hello World 1 2 12 # therefore, we do not need to use xargs . References . Linux manual page | Linux Command List |",
            "url": "https://ian729.github.io/silver-umbrella/markdown/tech/2022/10/02/ShellXargs.html",
            "relUrl": "/markdown/tech/2022/10/02/ShellXargs.html",
            "date": " • Oct 2, 2022"
        }
        
    
  
    
        ,"post2": {
            "title": "Object Detection using YOLOv5",
            "content": "Introduction . Repository: https://github.com/Ian729/yolov5 Dataset: https://cocodataset.org/#home Dataset Categories: https://gist.github.com/SrikarNamburu/0945de8f9a8714ec245dde3443e9d487 . Installation . git clone https://github.com/Ian729/yolov5 # clone cd yolov5 pip install -r requirements.txt # install . Usage . Inference with detect.py . detect.py runs inference on a variety of sources, downloading models automatically from the latest YOLOv5 release and saving results to runs/detect. . python detect.py --source 0 # webcam img.jpg # image vid.mp4 # video screen # screenshot path/ # directory &#39;path/*.jpg&#39; # glob &#39;https://youtu.be/Zgi9g1ksQHc&#39; # YouTube &#39;rtsp://example.com/media.mp4&#39; # RTSP, RTMP, HTTP stream . Inference . YOLOv5 PyTorch Hub inference. Models download automatically from the latest YOLOv5 release. . import torch # Model model = torch.hub.load(&#39;ultralytics/yolov5&#39;, &#39;yolov5s&#39;) # or yolov5n - yolov5x6, custom # Images img = &#39;https://ultralytics.com/images/zidane.jpg&#39; # or file, Path, PIL, OpenCV, numpy, list # Inference results = model(img) # Results results.print() # or .show(), .save(), .crop(), .pandas(), etc. .",
            "url": "https://ian729.github.io/silver-umbrella/markdown/tech/2022/09/30/ObjectDetection.html",
            "relUrl": "/markdown/tech/2022/09/30/ObjectDetection.html",
            "date": " • Sep 30, 2022"
        }
        
    
  
    
        ,"post3": {
            "title": "Hacking Chrome Dinosaur Game",
            "content": "Introducing Chrome Dinosaur Game . The Dinosaur Game (also known as the Chrome Dino) is a browser game developed by Google and built into the Google Chrome web browser. The player guides a pixelated Tyrannosaurus rex across a side-scrolling landscape, avoiding obstacles to achieve a higher score. The game was created by members of the Chrome UX team in 2014. . The game we are talking about in this blog refers to the Dino game ripped off from The Chromium Projects. . How to play . Using the spacebar to jump over the cacti and the birds. The game ends when the dinosaur collides with an obstacle or when the dinosaur falls into a pit. . Usage . Open Chrome Console and paste the following code: . Runner.prototype.gameOver() = function() {} . This will disable the game over function and you can play the game forever. . Runner.instance_.config.SPEED . This will return the current speed of the game. You can change the speed by changing the value of the variable. . Runner.instance_.setSpeed(60) // set speed to 10 times faster . In order to end the game, you can cache the gameOver function and call it when you want to end the game. . var cachedGameOver = Runner.prototype.gameOver; Runner.prototype.gameOver = function() { } . When you want to end the game and appear on the leaderbaord . Runner.prototype.gameOver = cachedGameOver; . Have Fun Hacking Games! . References . [1] Wikipedia . [2] The Chromium Projects . [3] Chrome Dino Game . [4] Chrome Dino Game Source Code .",
            "url": "https://ian729.github.io/silver-umbrella/markdown/tech/2022/09/30/Chromedino.html",
            "relUrl": "/markdown/tech/2022/09/30/Chromedino.html",
            "date": " • Sep 30, 2022"
        }
        
    
  
    
        ,"post4": {
            "title": "Python syntax sugar",
            "content": "Introduction . I have been using Python, and I noticed some interesting Pythonic way to avoid wring for loop and if-else statements . For Loop . List Comprehension/Generator . result = [] for item in item_list: new_item = do_something(item) result.append(new_item) . This is a typical example of transforming a list of items into another, and there is a very Pythonic implementation for that . result = [do_something(item) for item in item_list] . Function . If you want to use a function to transform the list, you can use map function . result = map(do_something, item_list) . For example . squared = map(lambda x: x**2, range(10)) . Extract Functions or Generators . The above two methods are very useful when you want to extract a function or generator from a list . How about more complicated examples? . results = [] for item in item_list: # setup # condition # processing # calculation results.append(result) . Obviously you are overloading a code block. . Instead, you can do: . results = [] def process(item) # setup # condition # processing # calculation return result results = [process(item) for item in item_list] . How about nested for loop? . results = [] for item in item_list: for sub_item in sub_item_list: # setup # condition # processing # calculation results.append(result) . To switch it to a list comprehension, you can do: . results = [process(item, sub_item) for item in item_list for sub_item in sub_item_list] . If you want to record some inner state of the list . a = [2,8,5,6,4,3,9,7,1] results = [] current = 0 for i in a: current = max(current, i) results.append(current) print(results) # [2, 8, 8, 8, 8, 8, 9, 9, 9] . We can use generator to do the same thing . def max_generator(a): current = 0 for i in a: current = max(current, i) yield current a = [2,8,5,6,4,3,9,7,1] results = list(max_generator(a)) print(results) # [2, 8, 8, 8, 8, 8, 9, 9, 9] . Wait a minute, is there a for loop in the generator? . We could do it with itertools.accumulate . import itertools a = [2,8,5,6,4,3,9,7,1] results = list(itertools.accumulate(a, max)) print(results) # [2, 8, 8, 8, 8, 8, 9, 9, 9] . If-Else . Ternary Operator . if condition: x = true_value else: x = false_value . can be written as . x = true_value if condition else false_value . Probability Space . if condition: x = true_value else: x = false_value . can also be written as . x = [false_value, true_value][condition] . Conclusion . Most of the time, you don’t need to write for loop and if-else statements, and you can use list comprehension, map, generator, ternary operator, and probability space to do the same thing. . I hope you find this post useful. If you have any questions, please contact me via email or GitHub .",
            "url": "https://ian729.github.io/silver-umbrella/markdown/tech/2022/09/02/Python.html",
            "relUrl": "/markdown/tech/2022/09/02/Python.html",
            "date": " • Sep 2, 2022"
        }
        
    
  
    
        ,"post5": {
            "title": "Figlet",
            "content": "Introduction . pyfiglet is the Python implementation of the FIGlet font rendering system. . Installation . pip3 install pyfiglet . Usage . &gt;&gt;&gt; import pyfiglet &gt;&gt;&gt; figlet_obj = pyfiglet.figlet_format(&quot;Hello World&quot;) &gt;&gt;&gt; print(figlet_obj) _ _ _ _ __ __ _ _ | | | | ___| | | ___ / /__ _ __| | __| | | |_| |/ _ | |/ _ / / / _ | &#39;__| |/ _` | | _ | __/ | | (_) | V V / (_) | | | | (_| | |_| |_| ___|_|_| ___/ _/ _/ ___/|_| |_| __,_| . Reference . geeksforgeeks |",
            "url": "https://ian729.github.io/silver-umbrella/markdown/tech/2022/08/13/Figlet.html",
            "relUrl": "/markdown/tech/2022/08/13/Figlet.html",
            "date": " • Aug 13, 2022"
        }
        
    
  
    
        ,"post6": {
            "title": "Fastpages Notebook Blog Post",
            "content": "About . This notebook is a demonstration of some of capabilities of fastpages with notebooks. . With fastpages you can save your jupyter notebooks into the _notebooks folder at the root of your repository, and they will be automatically be converted to Jekyll compliant blog posts! . Front Matter . The first cell in your Jupyter Notebook or markdown blog post contains front matter. Front matter is metadata that can turn on/off options in your Notebook. It is formatted like this: . # &quot;My Title&quot; &gt; &quot;Awesome summary&quot; - toc:true- branch: master - badges: true - comments: true - author: Hamel Husain &amp; Jeremy Howard - categories: [fastpages, jupyter] . Setting toc: true will automatically generate a table of contents | Setting badges: true will automatically include GitHub and Google Colab links to your notebook. | Setting comments: true will enable commenting on your blog post, powered by utterances. | . The title and description need to be enclosed in double quotes only if they include special characters such as a colon. More details and options for front matter can be viewed on the front matter section of the README. . Markdown Shortcuts . A #hide comment at the top of any code cell will hide both the input and output of that cell in your blog post. . A #hide_input comment at the top of any code cell will only hide the input of that cell. . The comment #hide_input was used to hide the code that produced this. . put a #collapse-hide flag at the top of any cell if you want to hide that cell by default, but give the reader the option to show it: . import pandas as pd import altair as alt . . put a #collapse-show flag at the top of any cell if you want to show that cell by default, but give the reader the option to hide it: . cars = &#39;https://vega.github.io/vega-datasets/data/cars.json&#39; movies = &#39;https://vega.github.io/vega-datasets/data/movies.json&#39; sp500 = &#39;https://vega.github.io/vega-datasets/data/sp500.csv&#39; stocks = &#39;https://vega.github.io/vega-datasets/data/stocks.csv&#39; flights = &#39;https://vega.github.io/vega-datasets/data/flights-5k.json&#39; . . place a #collapse-output flag at the top of any cell if you want to put the output under a collapsable element that is closed by default, but give the reader the option to open it: . print(&#39;The comment #collapse-output was used to collapse the output of this cell by default but you can expand it.&#39;) . The comment #collapse-output was used to collapse the output of this cell by default but you can expand it. . . Interactive Charts With Altair . Charts made with Altair remain interactive. Example charts taken from this repo, specifically this notebook. . Example 1: DropDown . # use specific hard-wired values as the initial selected values selection = alt.selection_single( name=&#39;Select&#39;, fields=[&#39;Major_Genre&#39;, &#39;MPAA_Rating&#39;], init={&#39;Major_Genre&#39;: &#39;Drama&#39;, &#39;MPAA_Rating&#39;: &#39;R&#39;}, bind={&#39;Major_Genre&#39;: alt.binding_select(options=genres), &#39;MPAA_Rating&#39;: alt.binding_radio(options=mpaa)} ) # scatter plot, modify opacity based on selection alt.Chart(df).mark_circle().add_selection( selection ).encode( x=&#39;Rotten_Tomatoes_Rating:Q&#39;, y=&#39;IMDB_Rating:Q&#39;, tooltip=&#39;Title:N&#39;, opacity=alt.condition(selection, alt.value(0.75), alt.value(0.05)) ) . Example 2: Tooltips . alt.Chart(df).mark_circle().add_selection( alt.selection_interval(bind=&#39;scales&#39;, encodings=[&#39;x&#39;]) ).encode( alt.X(&#39;Rotten_Tomatoes_Rating&#39;, type=&#39;quantitative&#39;), alt.Y(&#39;IMDB_Rating&#39;, type=&#39;quantitative&#39;, axis=alt.Axis(minExtent=30)), # y=alt.Y(&#39;IMDB_Rating:Q&#39;, ), # use min extent to stabilize axis title placement tooltip=[&#39;Title:N&#39;, &#39;Release_Date:N&#39;, &#39;IMDB_Rating:Q&#39;, &#39;Rotten_Tomatoes_Rating:Q&#39;] ).properties( width=500, height=400 ) . Example 3: More Tooltips . label = alt.selection_single( encodings=[&#39;x&#39;], # limit selection to x-axis value on=&#39;mouseover&#39;, # select on mouseover events nearest=True, # select data point nearest the cursor empty=&#39;none&#39; # empty selection includes no data points ) # define our base line chart of stock prices base = alt.Chart().mark_line().encode( alt.X(&#39;date:T&#39;), alt.Y(&#39;price:Q&#39;, scale=alt.Scale(type=&#39;log&#39;)), alt.Color(&#39;symbol:N&#39;) ) alt.layer( base, # base line chart # add a rule mark to serve as a guide line alt.Chart().mark_rule(color=&#39;#aaa&#39;).encode( x=&#39;date:T&#39; ).transform_filter(label), # add circle marks for selected time points, hide unselected points base.mark_circle().encode( opacity=alt.condition(label, alt.value(1), alt.value(0)) ).add_selection(label), # add white stroked text to provide a legible background for labels base.mark_text(align=&#39;left&#39;, dx=5, dy=-5, stroke=&#39;white&#39;, strokeWidth=2).encode( text=&#39;price:Q&#39; ).transform_filter(label), # add text labels for stock prices base.mark_text(align=&#39;left&#39;, dx=5, dy=-5).encode( text=&#39;price:Q&#39; ).transform_filter(label), data=stocks ).properties( width=500, height=400 ) . Data Tables . You can display tables per the usual way in your blog: . df[[&#39;Title&#39;, &#39;Worldwide_Gross&#39;, &#39;Production_Budget&#39;, &#39;Distributor&#39;, &#39;MPAA_Rating&#39;, &#39;IMDB_Rating&#39;, &#39;Rotten_Tomatoes_Rating&#39;]].head() . Title Worldwide_Gross Production_Budget Distributor MPAA_Rating IMDB_Rating Rotten_Tomatoes_Rating . 0 The Land Girls | 146083.0 | 8000000.0 | Gramercy | R | 6.1 | NaN | . 1 First Love, Last Rites | 10876.0 | 300000.0 | Strand | R | 6.9 | NaN | . 2 I Married a Strange Person | 203134.0 | 250000.0 | Lionsgate | None | 6.8 | NaN | . 3 Let&#39;s Talk About Sex | 373615.0 | 300000.0 | Fine Line | None | NaN | 13.0 | . 4 Slam | 1087521.0 | 1000000.0 | Trimark | R | 3.4 | 62.0 | . Images . Local Images . You can reference local images and they will be copied and rendered on your blog automatically. You can include these with the following markdown syntax: . ![](my_icons/fastai_logo.png) . . Remote Images . Remote images can be included with the following markdown syntax: . ![](https://image.flaticon.com/icons/svg/36/36686.svg) . . Animated Gifs . Animated Gifs work, too! . ![](https://upload.wikimedia.org/wikipedia/commons/7/71/ChessPawnSpecialMoves.gif) . . Captions . You can include captions with markdown images like this: . ![](https://www.fast.ai/images/fastai_paper/show_batch.png &quot;Credit: https://www.fast.ai/2020/02/13/fastai-A-Layered-API-for-Deep-Learning/&quot;) . . Other Elements . GitHub Flavored Emojis . Typing I give this post two :+1:! will render this: . I give this post two :+1:! . Tweetcards . Typing &gt; twitter: https://twitter.com/jakevdp/status/1204765621767901185?s=20 will render this: Altair 4.0 is released! https://t.co/PCyrIOTcvvTry it with: pip install -U altairThe full list of changes is at https://t.co/roXmzcsT58 ...read on for some highlights. pic.twitter.com/vWJ0ZveKbZ . &mdash; Jake VanderPlas (@jakevdp) December 11, 2019 . Youtube Videos . Typing &gt; youtube: https://youtu.be/XfoYk_Z5AkI will render this: . Boxes / Callouts . Typing &gt; Warning: There will be no second warning! will render this: . Warning: There will be no second warning! . Typing &gt; Important: Pay attention! It&#39;s important. will render this: . Important: Pay attention! It&#8217;s important. . Typing &gt; Tip: This is my tip. will render this: . Tip: This is my tip. . Typing &gt; Note: Take note of this. will render this: . Note: Take note of this. . Typing &gt; Note: A doc link to [an example website: fast.ai](https://www.fast.ai/) should also work fine. will render in the docs: . Note: A doc link to an example website: fast.ai should also work fine. . Footnotes . You can have footnotes in notebooks, however the syntax is different compared to markdown documents. This guide provides more detail about this syntax, which looks like this: . For example, here is a footnote {% fn 1 %}. And another {% fn 2 %} {{ &#39;This is the footnote.&#39; | fndetail: 1 }} {{ &#39;This is the other footnote. You can even have a [link](www.github.com)!&#39; | fndetail: 2 }} . For example, here is a footnote 1. . And another 2 . 1. This is the footnote.↩ . 2. This is the other footnote. You can even have a link!↩ .",
            "url": "https://ian729.github.io/silver-umbrella/jupyter/2020/02/20/test.html",
            "relUrl": "/jupyter/2020/02/20/test.html",
            "date": " • Feb 20, 2020"
        }
        
    
  
    
        ,"post7": {
            "title": "An Example Markdown Post",
            "content": "Example Markdown Post . Basic setup . Jekyll requires blog post files to be named according to the following format: . YEAR-MONTH-DAY-filename.md . Where YEAR is a four-digit number, MONTH and DAY are both two-digit numbers, and filename is whatever file name you choose, to remind yourself what this post is about. .md is the file extension for markdown files. . The first line of the file should start with a single hash character, then a space, then your title. This is how you create a “level 1 heading” in markdown. Then you can create level 2, 3, etc headings as you wish but repeating the hash character, such as you see in the line ## File names above. . Basic formatting . You can use italics, bold, code font text, and create links. Here’s a footnote 1. Here’s a horizontal rule: . . Lists . Here’s a list: . item 1 | item 2 | . And a numbered list: . item 1 | item 2 | Boxes and stuff . This is a quotation . . You can include alert boxes …and… . . You can include info boxes Images . . Code . You can format text and code per usual . General preformatted text: . # Do a thing do_thing() . Python code and output: . # Prints &#39;2&#39; print(1+1) . 2 . Formatting text as shell commands: . echo &quot;hello world&quot; ./some_script.sh --option &quot;value&quot; wget https://example.com/cat_photo1.png . Formatting text as YAML: . key: value - another_key: &quot;another value&quot; . Tables . Column 1 Column 2 . A thing | Another thing | . Tweetcards . Altair 4.0 is released! https://t.co/PCyrIOTcvvTry it with: pip install -U altairThe full list of changes is at https://t.co/roXmzcsT58 ...read on for some highlights. pic.twitter.com/vWJ0ZveKbZ . &mdash; Jake VanderPlas (@jakevdp) December 11, 2019 Footnotes . This is the footnote. &#8617; . |",
            "url": "https://ian729.github.io/silver-umbrella/markdown/tech/2020/01/14/test-markdown-post.html",
            "relUrl": "/markdown/tech/2020/01/14/test-markdown-post.html",
            "date": " • Jan 14, 2020"
        }
        
    
  

  
  

  
      ,"page1": {
          "title": "About Me",
          "content": "1996.07.29, 江苏无锡人，现居北京。 . 本科毕业于加拿大多伦多大学计算机科学系. . 研究生毕业于新加坡南洋理工大学人工智能系。 . 曾任职于Bell Canada，华为，目前任职于苹果，从事软件工程师。 . 理工男，对技术感兴趣，包括但不限于人工智能，网络安全，软件工程，数据科学。 . 伪文青，喜欢看小说，喜欢的作者有刘慈欣，加缪，阿加莎，东野圭吾。 . . “In a world where you can be anything, be kind” . . 1996/07/29 Born in Wuxi, Jiangsu, China, now living in Beijing. . Bachelor of Science in Computer Science from University of Toronto, Canada. . Master of Science in Artificial Intelligence from Nanyang Technological University, Singapore. . Worked at Bell Canada, Huawei, now working at Apple as a Software Engineer. . Geek, interested in technology, including but not limited to AI, Network Security, Software Engineering, Data Science. . Bookworm, like reading novels, favorite authors are Liu Cixin, Albert Camus, Agatha Christie, Keigo Higashino. .",
          "url": "https://ian729.github.io/silver-umbrella/about/",
          "relUrl": "/about/",
          "date": ""
      }
      
  

  

  
  

  

  
  

  

  
  

  
  

  
  

  
      ,"page10": {
          "title": "",
          "content": "Sitemap: {{ “sitemap.xml” | absolute_url }} | .",
          "url": "https://ian729.github.io/silver-umbrella/robots.txt",
          "relUrl": "/robots.txt",
          "date": ""
      }
      
  

}